pydltools/__init__.py
pydltools/Converter/__init__.py
pydltools/Converter/img2vid.py
pydltools/Converter/vid2img.py
pydltools-0.1.1.dist-info/LICENSE
pydltools-0.1.1.dist-info/METADATA
pydltools-0.1.1.dist-info/WHEEL
pydltools-0.1.1.dist-info/top_level.txt
pydltools-0.1.1.dist-info/RECORD
